blti.py
blti-0.1.8.dist-info/METADATA
blti-0.1.8.dist-info/RECORD
blti-0.1.8.dist-info/WHEEL
blti-0.1.8.dist-info/top_level.txt
