Metadata-Version: 2.1
Name: blti
Version: 0.1.8
Summary: py-blti: basic LTI authentication for python/django
Home-page: https://github.com/dcollien/py-blti
Author: David Collien
Author-email: me@dcollien.com
License: MIT
Platform: any
Requires-Dist: oauth2
